[{"id":"110100","value":"北京","parentId":"110000"},{"id":"120100","value":"天津","parentId":"120000"},{"id":"130100","value":"石家庄","parentId":"130000"},{"id":"130200","value":"唐山","parentId":"130000"},{"id":"130300","value":"秦皇岛","parentId":"130000"},{"id":"130400","value":"邯郸","parentId":"130000"},{"id":"130500","value":"邢台","parentId":"130000"},{"id":"130600","value":"保定","parentId":"130000"},{"id":"130700","value":"张家口","parentId":"130000"},{"id":"130800","value":"承德","parentId":"130000"},{"id":"130900","value":"沧州","parentId":"130000"},{"id":"131000","value":"廊坊","parentId":"130000"},{"id":"131100","value":"衡水","parentId":"130000"},{"id":"140100","value":"太原","parentId":"140000"},{"id":"140200","value":"大同","parentId":"140000"},{"id":"140300","value":"阳泉","parentId":"140000"},{"id":"140400","value":"长治","parentId":"140000"},{"id":"140500","value":"晋城","parentId":"140000"},{"id":"140600","value":"朔州","parentId":"140000"},{"id":"140700","value":"晋中","parentId":"140000"},{"id":"140800","value":"运城","parentId":"140000"},{"id":"140900","value":"忻州","parentId":"140000"},{"id":"141000","value":"临汾","parentId":"140000"},{"id":"141100","value":"吕梁","parentId":"140000"},{"id":"150100","value":"呼和浩特","parentId":"150000"},{"id":"150200","value":"包头","parentId":"150000"},{"id":"150300","value":"乌海","parentId":"150000"},{"id":"150400","value":"赤峰","parentId":"150000"},{"id":"150500","value":"通辽","parentId":"150000"},{"id":"150600","value":"鄂尔多斯","parentId":"150000"},{"id":"150700","value":"呼伦贝尔","parentId":"150000"},{"id":"150800","value":"巴彦淖尔","parentId":"150000"},{"id":"150900","value":"乌兰察布","parentId":"150000"},{"id":"152200","value":"兴安","parentId":"150000"},{"id":"152500","value":"锡林郭勒","parentId":"150000"},{"id":"152900","value":"阿拉善","parentId":"150000"},{"id":"210100","value":"沈阳","parentId":"210000"},{"id":"210200","value":"大连","parentId":"210000"},{"id":"210300","value":"鞍山","parentId":"210000"},{"id":"210400","value":"抚顺","parentId":"210000"},{"id":"210500","value":"本溪","parentId":"210000"},{"id":"210600","value":"丹东","parentId":"210000"},{"id":"210700","value":"锦州","parentId":"210000"},{"id":"210800","value":"营口","parentId":"210000"},{"id":"210900","value":"阜新","parentId":"210000"},{"id":"211000","value":"辽阳","parentId":"210000"},{"id":"211100","value":"盘锦","parentId":"210000"},{"id":"211200","value":"铁岭","parentId":"210000"},{"id":"211300","value":"朝阳","parentId":"210000"},{"id":"211400","value":"葫芦岛","parentId":"210000"},{"id":"220100","value":"长春","parentId":"220000"},{"id":"220200","value":"吉林","parentId":"220000"},{"id":"220300","value":"四平","parentId":"220000"},{"id":"220400","value":"辽源","parentId":"220000"},{"id":"220500","value":"通化","parentId":"220000"},{"id":"220600","value":"白山","parentId":"220000"},{"id":"220700","value":"松原","parentId":"220000"},{"id":"220800","value":"白城","parentId":"220000"},{"id":"222400","value":"延边","parentId":"220000"},{"id":"230100","value":"哈尔滨","parentId":"230000"},{"id":"230200","value":"齐齐哈尔","parentId":"230000"},{"id":"230300","value":"鸡西","parentId":"230000"},{"id":"230400","value":"鹤岗","parentId":"230000"},{"id":"230500","value":"双鸭山","parentId":"230000"},{"id":"230600","value":"大庆","parentId":"230000"},{"id":"230700","value":"伊春","parentId":"230000"},{"id":"230800","value":"佳木斯","parentId":"230000"},{"id":"230900","value":"七台河","parentId":"230000"},{"id":"231000","value":"牡丹江","parentId":"230000"},{"id":"231100","value":"黑河","parentId":"230000"},{"id":"231200","value":"绥化","parentId":"230000"},{"id":"232700","value":"大兴安岭","parentId":"230000"},{"id":"310100","value":"上海","parentId":"310000"},{"id":"320100","value":"南京","parentId":"320000"},{"id":"320200","value":"无锡","parentId":"320000"},{"id":"320300","value":"徐州","parentId":"320000"},{"id":"320400","value":"常州","parentId":"320000"},{"id":"320500","value":"苏州","parentId":"320000"},{"id":"320600","value":"南通","parentId":"320000"},{"id":"320700","value":"连云港","parentId":"320000"},{"id":"320800","value":"淮安","parentId":"320000"},{"id":"320900","value":"盐城","parentId":"320000"},{"id":"321000","value":"扬州","parentId":"320000"},{"id":"321100","value":"镇江","parentId":"320000"},{"id":"321200","value":"泰州","parentId":"320000"},{"id":"321300","value":"宿迁","parentId":"320000"},{"id":"330100","value":"杭州","parentId":"330000"},{"id":"330200","value":"宁波","parentId":"330000"},{"id":"330300","value":"温州","parentId":"330000"},{"id":"330400","value":"嘉兴","parentId":"330000"},{"id":"330500","value":"湖州","parentId":"330000"},{"id":"330600","value":"绍兴","parentId":"330000"},{"id":"330700","value":"金华","parentId":"330000"},{"id":"330800","value":"衢州","parentId":"330000"},{"id":"330900","value":"舟山","parentId":"330000"},{"id":"331000","value":"台州","parentId":"330000"},{"id":"331100","value":"丽水","parentId":"330000"},{"id":"340100","value":"合肥","parentId":"340000"},{"id":"340200","value":"芜湖","parentId":"340000"},{"id":"340300","value":"蚌埠","parentId":"340000"},{"id":"340400","value":"淮南","parentId":"340000"},{"id":"340500","value":"马鞍山","parentId":"340000"},{"id":"340600","value":"淮北","parentId":"340000"},{"id":"340700","value":"铜陵","parentId":"340000"},{"id":"340800","value":"安庆","parentId":"340000"},{"id":"341000","value":"黄山","parentId":"340000"},{"id":"341100","value":"滁州","parentId":"340000"},{"id":"341200","value":"阜阳","parentId":"340000"},{"id":"341300","value":"宿州","parentId":"340000"},{"id":"341400","value":"巢湖","parentId":"340000"},{"id":"341500","value":"六安","parentId":"340000"},{"id":"341600","value":"亳州","parentId":"340000"},{"id":"341700","value":"池州","parentId":"340000"},{"id":"341800","value":"宣城","parentId":"340000"},{"id":"350100","value":"福州","parentId":"350000"},{"id":"350200","value":"厦门","parentId":"350000"},{"id":"350300","value":"莆田","parentId":"350000"},{"id":"350400","value":"三明","parentId":"350000"},{"id":"350500","value":"泉州","parentId":"350000"},{"id":"350600","value":"漳州","parentId":"350000"},{"id":"350700","value":"南平","parentId":"350000"},{"id":"350800","value":"龙岩","parentId":"350000"},{"id":"350900","value":"宁德","parentId":"350000"},{"id":"360100","value":"南昌","parentId":"360000"},{"id":"360200","value":"景德镇","parentId":"360000"},{"id":"360202","value":"昌江","parentId":"460000"},{"id":"360300","value":"萍乡","parentId":"360000"},{"id":"360400","value":"九江","parentId":"360000"},{"id":"360500","value":"新余","parentId":"360000"},{"id":"360600","value":"鹰潭","parentId":"360000"},{"id":"360700","value":"赣州","parentId":"360000"},{"id":"360800","value":"吉安","parentId":"360000"},{"id":"360900","value":"宜春","parentId":"360000"},{"id":"361000","value":"抚州","parentId":"360000"},{"id":"361100","value":"上饶","parentId":"360000"},{"id":"370100","value":"济南","parentId":"370000"},{"id":"370200","value":"青岛","parentId":"370000"},{"id":"370300","value":"淄博","parentId":"370000"},{"id":"370400","value":"枣庄","parentId":"370000"},{"id":"370500","value":"东营","parentId":"370000"},{"id":"370600","value":"烟台","parentId":"370000"},{"id":"370700","value":"潍坊","parentId":"370000"},{"id":"370800","value":"济宁","parentId":"370000"},{"id":"370900","value":"泰安","parentId":"370000"},{"id":"371000","value":"威海","parentId":"370000"},{"id":"371100","value":"日照","parentId":"370000"},{"id":"371200","value":"莱芜","parentId":"370000"},{"id":"371300","value":"临沂","parentId":"370000"},{"id":"371400","value":"德州","parentId":"370000"},{"id":"371500","value":"聊城","parentId":"370000"},{"id":"371600","value":"滨州","parentId":"370000"},{"id":"371700","value":"菏泽","parentId":"370000"},{"id":"410100","value":"郑州","parentId":"410000"},{"id":"410200","value":"开封","parentId":"410000"},{"id":"410300","value":"洛阳","parentId":"410000"},{"id":"410400","value":"平顶山","parentId":"410000"},{"id":"410500","value":"安阳","parentId":"410000"},{"id":"410600","value":"鹤壁","parentId":"410000"},{"id":"410700","value":"新乡","parentId":"410000"},{"id":"410800","value":"焦作","parentId":"410000"},{"id":"410900","value":"濮阳","parentId":"410000"},{"id":"411000","value":"许昌","parentId":"410000"},{"id":"411100","value":"漯河","parentId":"410000"},{"id":"411200","value":"三门峡","parentId":"410000"},{"id":"411300","value":"南阳","parentId":"410000"},{"id":"411400","value":"商丘","parentId":"410000"},{"id":"411500","value":"信阳","parentId":"410000"},{"id":"411600","value":"周口","parentId":"410000"},{"id":"411700","value":"驻马店","parentId":"410000"},{"id":"420100","value":"武汉","parentId":"420000"},{"id":"420200","value":"黄石","parentId":"420000"},{"id":"420300","value":"十堰","parentId":"420000"},{"id":"420500","value":"宜昌","parentId":"420000"},{"id":"420600","value":"襄阳","parentId":"420000"},{"id":"420700","value":"鄂州","parentId":"420000"},{"id":"420800","value":"荆门","parentId":"420000"},{"id":"420900","value":"孝感","parentId":"420000"},{"id":"421000","value":"荆州","parentId":"420000"},{"id":"421100","value":"黄冈","parentId":"420000"},{"id":"421200","value":"咸宁","parentId":"420000"},{"id":"421300","value":"随州","parentId":"420000"},{"id":"422800","value":"恩施","parentId":"420000"},{"id":"429004","value":"仙桃","parentId":"420000"},{"id":"429005","value":"潜江","parentId":"420000"},{"id":"429006","value":"天门","parentId":"420000"},{"id":"429021","value":"神农架林区","parentId":"420000"},{"id":"430100","value":"长沙","parentId":"430000"},{"id":"430200","value":"株洲","parentId":"430000"},{"id":"430300","value":"湘潭","parentId":"430000"},{"id":"430400","value":"衡阳","parentId":"430000"},{"id":"430500","value":"邵阳","parentId":"430000"},{"id":"430600","value":"岳阳","parentId":"430000"},{"id":"430700","value":"常德","parentId":"430000"},{"id":"430800","value":"张家界","parentId":"430000"},{"id":"430900","value":"益阳","parentId":"430000"},{"id":"431000","value":"郴州","parentId":"430000"},{"id":"431100","value":"永州","parentId":"430000"},{"id":"431200","value":"怀化","parentId":"430000"},{"id":"431300","value":"娄底","parentId":"430000"},{"id":"433100","value":"湘西","parentId":"430000"},{"id":"440100","value":"广州","parentId":"440000"},{"id":"440200","value":"韶关","parentId":"440000"},{"id":"440300","value":"深圳","parentId":"440000"},{"id":"440400","value":"珠海","parentId":"440000"},{"id":"440500","value":"汕头","parentId":"440000"},{"id":"440600","value":"佛山","parentId":"440000"},{"id":"440700","value":"江门","parentId":"440000"},{"id":"440800","value":"湛江","parentId":"440000"},{"id":"440900","value":"茂名","parentId":"440000"},{"id":"441200","value":"肇庆","parentId":"440000"},{"id":"441300","value":"惠州","parentId":"440000"},{"id":"441400","value":"梅州","parentId":"440000"},{"id":"441500","value":"汕尾","parentId":"440000"},{"id":"441600","value":"河源","parentId":"440000"},{"id":"441700","value":"阳江","parentId":"440000"},{"id":"441800","value":"清远","parentId":"440000"},{"id":"441900","value":"东莞","parentId":"440000"},{"id":"442000","value":"中山","parentId":"440000"},{"id":"445100","value":"潮州","parentId":"440000"},{"id":"445200","value":"揭阳","parentId":"440000"},{"id":"445300","value":"云浮","parentId":"440000"},{"id":"450100","value":"南宁","parentId":"450000"},{"id":"450200","value":"柳州","parentId":"450000"},{"id":"450300","value":"桂林","parentId":"450000"},{"id":"450400","value":"梧州","parentId":"450000"},{"id":"450500","value":"北海","parentId":"450000"},{"id":"450600","value":"防城港","parentId":"450000"},{"id":"450700","value":"钦州","parentId":"450000"},{"id":"450800","value":"贵港","parentId":"450000"},{"id":"450900","value":"玉林","parentId":"450000"},{"id":"451000","value":"百色","parentId":"450000"},{"id":"451100","value":"贺州","parentId":"450000"},{"id":"451200","value":"河池","parentId":"450000"},{"id":"451300","value":"来宾","parentId":"450000"},{"id":"451400","value":"崇左","parentId":"450000"},{"id":"460100","value":"海口","parentId":"460000"},{"id":"460200","value":"三亚","parentId":"460000"},{"id":"469001","value":"五指山","parentId":"460000"},{"id":"469002","value":"琼海","parentId":"460000"},{"id":"469003","value":"儋州","parentId":"460000"},{"id":"469005","value":"文昌","parentId":"460000"},{"id":"469006","value":"万宁","parentId":"460000"},{"id":"469007","value":"东方","parentId":"460000"},{"id":"469021","value":"定安","parentId":"460000"},{"id":"469022","value":"屯昌","parentId":"460000"},{"id":"469024","value":"临高","parentId":"460000"},{"id":"469025","value":"白沙","parentId":"460000"},{"id":"469027","value":"乐东","parentId":"460000"},{"id":"469028","value":"陵水","parentId":"460000"},{"id":"469029","value":"保亭","parentId":"460000"},{"id":"469030","value":"琼中","parentId":"460000"},{"id":"500100","value":"重庆","parentId":"500000"},{"id":"510100","value":"成都","parentId":"510000"},{"id":"510300","value":"自贡","parentId":"510000"},{"id":"510400","value":"攀枝花","parentId":"510000"},{"id":"510500","value":"泸州","parentId":"510000"},{"id":"510600","value":"德阳","parentId":"510000"},{"id":"510700","value":"绵阳","parentId":"510000"},{"id":"510800","value":"广元","parentId":"510000"},{"id":"510900","value":"遂宁","parentId":"510000"},{"id":"511000","value":"内江","parentId":"510000"},{"id":"511100","value":"乐山","parentId":"510000"},{"id":"511300","value":"南充","parentId":"510000"},{"id":"511400","value":"眉山","parentId":"510000"},{"id":"511500","value":"宜宾","parentId":"510000"},{"id":"511600","value":"广安","parentId":"510000"},{"id":"511700","value":"达州","parentId":"510000"},{"id":"511800","value":"雅安","parentId":"510000"},{"id":"511900","value":"巴中","parentId":"510000"},{"id":"512000","value":"资阳","parentId":"510000"},{"id":"513200","value":"阿坝","parentId":"510000"},{"id":"513300","value":"甘孜","parentId":"510000"},{"id":"513400","value":"凉山","parentId":"510000"},{"id":"520100","value":"贵阳","parentId":"520000"},{"id":"520200","value":"六盘水","parentId":"520000"},{"id":"520300","value":"遵义","parentId":"520000"},{"id":"520400","value":"安顺","parentId":"520000"},{"id":"522200","value":"铜仁","parentId":"520000"},{"id":"522300","value":"黔西南","parentId":"520000"},{"id":"522400","value":"毕节","parentId":"520000"},{"id":"522600","value":"黔东南","parentId":"520000"},{"id":"522700","value":"黔南","parentId":"520000"},{"id":"530100","value":"昆明","parentId":"530000"},{"id":"530300","value":"曲靖","parentId":"530000"},{"id":"530400","value":"玉溪","parentId":"530000"},{"id":"530500","value":"保山","parentId":"530000"},{"id":"530600","value":"昭通","parentId":"530000"},{"id":"530700","value":"丽江","parentId":"530000"},{"id":"530800","value":"普洱","parentId":"530000"},{"id":"530900","value":"临沧","parentId":"530000"},{"id":"532300","value":"楚雄","parentId":"530000"},{"id":"532500","value":"红河","parentId":"530000"},{"id":"532600","value":"文山","parentId":"530000"},{"id":"532800","value":"西双版纳","parentId":"530000"},{"id":"532900","value":"大理","parentId":"530000"},{"id":"533100","value":"德宏","parentId":"530000"},{"id":"533300","value":"怒江","parentId":"530000"},{"id":"533400","value":"迪庆","parentId":"530000"},{"id":"540100","value":"拉萨","parentId":"540000"},{"id":"542100","value":"昌都","parentId":"540000"},{"id":"542200","value":"山南","parentId":"540000"},{"id":"542300","value":"日喀则","parentId":"540000"},{"id":"542400","value":"那曲","parentId":"540000"},{"id":"542500","value":"阿里","parentId":"540000"},{"id":"542600","value":"林芝","parentId":"540000"},{"id":"610100","value":"西安","parentId":"610000"},{"id":"610200","value":"铜川","parentId":"610000"},{"id":"610300","value":"宝鸡","parentId":"610000"},{"id":"610400","value":"咸阳","parentId":"610000"},{"id":"610500","value":"渭南","parentId":"610000"},{"id":"610600","value":"延安","parentId":"610000"},{"id":"610700","value":"汉中","parentId":"610000"},{"id":"610800","value":"榆林","parentId":"610000"},{"id":"610900","value":"安康","parentId":"610000"},{"id":"611000","value":"商洛","parentId":"610000"},{"id":"620100","value":"兰州","parentId":"620000"},{"id":"620200","value":"嘉峪关","parentId":"620000"},{"id":"620300","value":"金昌","parentId":"620000"},{"id":"620400","value":"白银","parentId":"620000"},{"id":"620500","value":"天水","parentId":"620000"},{"id":"620600","value":"武威","parentId":"620000"},{"id":"620700","value":"张掖","parentId":"620000"},{"id":"620800","value":"平凉","parentId":"620000"},{"id":"620900","value":"酒泉","parentId":"620000"},{"id":"621000","value":"庆阳","parentId":"620000"},{"id":"621100","value":"定西","parentId":"620000"},{"id":"621200","value":"陇南","parentId":"620000"},{"id":"622900","value":"临夏","parentId":"620000"},{"id":"623000","value":"甘南","parentId":"620000"},{"id":"630100","value":"西宁","parentId":"630000"},{"id":"632100","value":"海东","parentId":"630000"},{"id":"632200","value":"海北","parentId":"630000"},{"id":"632300","value":"黄南","parentId":"630000"},{"id":"632500","value":"海南","parentId":"630000"},{"id":"632600","value":"果洛","parentId":"630000"},{"id":"632700","value":"玉树","parentId":"630000"},{"id":"632800","value":"海西","parentId":"630000"},{"id":"640100","value":"银川","parentId":"640000"},{"id":"640200","value":"石嘴山","parentId":"640000"},{"id":"640300","value":"吴忠","parentId":"640000"},{"id":"640400","value":"固原","parentId":"640000"},{"id":"640500","value":"中卫","parentId":"640000"},{"id":"650100","value":"乌鲁木齐","parentId":"650000"},{"id":"650200","value":"克拉玛依","parentId":"650000"},{"id":"652100","value":"吐鲁番","parentId":"650000"},{"id":"652200","value":"哈密","parentId":"650000"},{"id":"652300","value":"昌吉","parentId":"650000"},{"id":"652700","value":"博尔塔拉","parentId":"650000"},{"id":"652800","value":"巴音郭楞","parentId":"650000"},{"id":"652900","value":"阿克苏","parentId":"650000"},{"id":"653000","value":"克孜勒苏","parentId":"650000"},{"id":"653100","value":"喀什","parentId":"650000"},{"id":"653200","value":"和田","parentId":"650000"},{"id":"654000","value":"伊犁","parentId":"650000"},{"id":"654200","value":"塔城","parentId":"650000"},{"id":"654300","value":"阿勒泰","parentId":"650000"},{"id":"659001","value":"石河子","parentId":"650000"},{"id":"659002","value":"阿拉尔","parentId":"650000"},{"id":"659004","value":"五家渠","parentId":"650000"},{"id":"710100","value":"台湾","parentId":"710000"},{"id":"810100","value":"香港","parentId":"810000"},{"id":"820100","value":"澳门","parentId":"820000"}]
